LICENSE
MANIFEST.in
README.rst
setup.py
twabulous/__init__.py
twabulous/twabulous.py
twabulous/twitmuncher.py
twabulous.egg-info/PKG-INFO
twabulous.egg-info/SOURCES.txt
twabulous.egg-info/dependency_links.txt
twabulous.egg-info/entry_points.txt
twabulous.egg-info/not-zip-safe
twabulous.egg-info/requires.txt
twabulous.egg-info/top_level.txt