Metadata-Version: 1.0
Name: twabulous
Version: 9000.4a
Summary: Twitter + Fabulous = Twabulous
Home-page: http://github.com/ralphbean/twabulous/
Author: Ralph Bean & Remy DeCausemaker
Author-email: ralph.bean@gmail.com
License: AGPLv3
Platform: UNKNOWN
